corut_utils/__about__.py
corut_utils/__init__.py
corut_utils/contenttypes.py
corut_utils/shell/__init__.py
corut_utils/shell/dotenv.py
corut_utils/shell/pipupdater.py
corut_utils/shell/utilssys.py
corut_utils/vcs/__init__.py
corut_utils/vcs/utilsgit.py
corut_utils-0.1.dist-info/METADATA
corut_utils-0.1.dist-info/WHEEL
corut_utils-0.1.dist-info/licenses/LICENSE
corut_utils-0.1.dist-info/RECORD
