Metadata-Version: 2.3
Name: corut-utils
Version: 0.1
Summary: Desktop/Web applications and include needs for many devices.
Project-URL: Documentation, https://www.ibrahimcorut.com/projects/pypi-corut_utils/overview
Project-URL: Source, https://www.ibrahimcorut.com/projects/pypi-corut_utils/code/tree/main
Project-URL: Issues, https://www.ibrahimcorut.com/projects/pypi-corut_utils/issues
Author-email: İbrahim CÖRÜT <ibrhmcorut@gmail.com>
License: MIT License
License-File: LICENSE
Keywords: corut,cörüt,utils
Classifier: Intended Audience :: Developers
Classifier: Programming Language :: Python :: 3.11
Classifier: Programming Language :: Python :: 3.12
Classifier: Programming Language :: Python :: 3.13
Classifier: Programming Language :: Python :: Implementation :: PyPy
Requires-Python: >=3.11
Requires-Dist: gitpython
Requires-Dist: pandas
